dict_from_g2pE/__init__.py
dict_from_g2pE/argparse_helper.py
dict_from_g2pE/cli.py
dict_from_g2pE/core.py
dict_from_g2pE/main.py
dict_from_g2pE-0.0.2.dist-info/LICENSE
dict_from_g2pE-0.0.2.dist-info/METADATA
dict_from_g2pE-0.0.2.dist-info/WHEEL
dict_from_g2pE-0.0.2.dist-info/entry_points.txt
dict_from_g2pE-0.0.2.dist-info/top_level.txt
dict_from_g2pE-0.0.2.dist-info/RECORD
